{"computer-graphics_render2screen.md":"2eb9be9c","computer-graphics_pipeline.md":"fa36a26c","computer-graphics_transformations.md":"c5674a5a","effective-cpp_07-virtual-destructor.md":"2b7aa609","computer-graphics_index.md":"d1d23b6f","effective-cpp_01-federation.md":"373a950b","computer-graphics_camera.md":"a2fa23c3","effective-cpp_03-use-const.md":"e51bc0e3","effective-cpp_06-refuse-explicitly.md":"80800295","computer-graphics_coordinate.md":"c82a0c93","2021_10_23_dev-tools-tech.md":"6cd880d2","computer-graphics_software.md":"c14610ff","computer-graphics_hardware.md":"85eb5cce","computer-graphics_opengl-pipeline.md":"1f80bdfa","2022_04_03_color.md":"c177807e","effective-cpp_05-default-fun.md":"557b7b5b","effective-cpp_10-assignment-operator.md":"f752d287","effective-cpp_11-assignment-self.md":"3177774f","effective-cpp_12-copy-object.md":"0dc10aa0","effective-cpp_08-destructor-exception.md":"aefd12c6","09_call_virtual_func.md":"05f45635","effective-cpp_04-init-obj.md":"8e85f5d6","2022_02_08_digital-audio.md":"a46d9043","index.md":"92c7eaaf","effective-cpp_index.md":"1cb57aad","computer-graphics_triangle.md":"5b6ef0ba","2023_04_16_electron-events.md":"1f00e638","categories.md":"71da6c33","effective-cpp_02-avoid-define.md":"d8124a93","2021_05_10_parallax-scrolling.md":"5ee59a84","2022_01_29_basic-concepts.md":"269f375a","2022_07_31_commitlint-custom.md":"9aaee8f8","computer-graphics_texture.md":"0851f402","2021_09_12_video-basic.md":"a25de5f4","2021_06_14_commitlint.md":"ddac106f","2019_12_16_redux.md":"f3546988","2021_04_12_koa.md":"d766eb7c","2019_12_16_promise.md":"75766479","2021_10_26_videojs-plugin.md":"0663b005","2021_12_12_videojs-languages.md":"ec99c63b","2022_04_28_videojs-logger.md":"19cbda28","2021_05_31_videojs.md":"6a638094","2023_05_28_fe-binary.md":"c4e43871","2020_02_21_react-redux.md":"68257996","2022_03_26_videojs-middleware.md":"e7a92278","2021_12_18_extensions.md":"bc90880d","2022_03_17_web-video-basic.md":"9a4ca5a5","2021_09_28_vmodel.md":"31d2bac3","tag.md":"7267e540","tags.md":"ac87e7ad","2021_05_09_egg.md":"2ede7b9f","2022_05_08_flv.md":"c88d6d8c","2022_05_29_videojs-tech.md":"c668a07a","2020_02_05_vuex.md":"49aba5c8","2022_05_05_videojs-modal.md":"7aaac432","2021_08_03_matrix.md":"f2279002","2023_11_05_vite.md":"7b653341"}
